zonal_variograms/__init__.py
zonal_variograms/__version__.py
zonal_variograms/cli.py
zonal_variograms/cli_deprecated.py
zonal_variograms/io.py
zonal_variograms/main.py
zonal_variograms/util.py
zonal_variograms-0.3.3.dist-info/LICENSE
zonal_variograms-0.3.3.dist-info/METADATA
zonal_variograms-0.3.3.dist-info/WHEEL
zonal_variograms-0.3.3.dist-info/entry_points.txt
zonal_variograms-0.3.3.dist-info/top_level.txt
zonal_variograms-0.3.3.dist-info/RECORD
